civ5_wallpapers-1.0.0.dist-info/WHEEL
civ5_wallpapers-1.0.0.dist-info/entry_points.txt
civ5_wallpapers-1.0.0.dist-info/metadata.json
civ5_wallpapers-1.0.0.dist-info/METADATA
civ5_wallpapers-1.0.0.dist-info/RECORD
civ5_wallpapers-1.0.0.dist-info/DESCRIPTION.rst
civ5_wallpapers-1.0.0.dist-info/top_level.txt
civ5_wallpapers/extractor.py
civ5_wallpapers/__init__.py
civ5_wallpapers/__main__.py
civ5_wallpapers/cli.py
civ5_wallpapers/fpk.py
civ5_wallpapers/applier.py
