Metadata-Version: 2.0
Name: civ5-wallpapers
Version: 1.0.0
Summary: Use Civilization V wallpapers on your Linux desktop
Home-page: https://github.com/pietroalbini/civ5-wallpapers
Author: Pietro Albini
Author-email: pietro@pietroalbini.org
License: GPL-3+
Platform: UNKNOWN
Classifier: Development Status :: 5 - Production/Stable
Classifier: Environment :: Console
Classifier: Environment :: X11 Applications
Classifier: Environment :: X11 Applications :: Gnome
Classifier: Intended Audience :: Other Audience
Classifier: License :: OSI Approved :: GNU General Public License v3 or later (GPLv3+)
Classifier: Programming Language :: Python :: 3
Classifier: Topic :: Desktop Environment :: Gnome
Classifier: Topic :: Games/Entertainment
Classifier: Topic :: Games/Entertainment :: Turn Based Strategy
Classifier: Topic :: Utilities
